setup.py
audit/__init__.py
audit/bind.py
audit/models.py
audit/signals.py
audit.egg-info/PKG-INFO
audit.egg-info/SOURCES.txt
audit.egg-info/dependency_links.txt
audit.egg-info/top_level.txt