Metadata-Version: 1.0
Name: audit
Version: 0.2-beta-2
Summary: This is a fairly comprehensive Audit Trail App for use with standard RDBMS databases.
Home-page: http://code.google.com/p/django-audit/
Author: Dj Gilcrease
Author-email: digitalxero@gmail.com
License: UNKNOWN
Download-URL: http://django-audit.googlecode.com/files/
Keywords: django,audit
Platform: UNKNOWN
Classifier: Development Status :: 4 - Beta
Classifier: Environment :: Web Environment
Classifier: Framework :: Django
Classifier: Intended Audience :: Developers
Classifier: License :: OSI Approved :: BSD License
Classifier: Operating System :: OS Independent
Classifier: Programming Language :: Python :: 2
Classifier: Topic :: Internet :: WWW/HTTP
Classifier: Topic :: Internet :: WWW/HTTP :: Dynamic Content
Classifier: Topic :: Software Development :: Libraries :: Python Modules
